README.md
setup.py
nextdnn/__init__.py
nextdnn/version.py
nextdnn.egg-info/PKG-INFO
nextdnn.egg-info/SOURCES.txt
nextdnn.egg-info/dependency_links.txt
nextdnn.egg-info/top_level.txt