Metadata-Version: 2.1
Name: nextdnn
Version: 0.0.1
Summary: nextdnn
Home-page: https://github.com/quanhua92/nextdnn
Author: Quan Hua
Author-email: support@nextdnn.com
License: MIT
Platform: UNKNOWN
Classifier: License :: OSI Approved :: MIT License
Classifier: Programming Language :: Python :: 3
Classifier: Programming Language :: Python :: 3.5
Classifier: Programming Language :: Python :: 3.6
Classifier: Programming Language :: Python :: 3.7
Classifier: Programming Language :: Python :: 3.8
